BlackDynamite/BDstat.py
BlackDynamite/__init__.py
BlackDynamite/base.py
BlackDynamite/base_zeo.py
BlackDynamite/bd_constraints.py
BlackDynamite/bd_transactions.py
BlackDynamite/bdlogging.py
BlackDynamite/bdparser.py
BlackDynamite/conffile_zeo.py
BlackDynamite/constraints_zeo.py
BlackDynamite/graphhelper.py
BlackDynamite/job.py
BlackDynamite/jobselector.py
BlackDynamite/loader.py
BlackDynamite/lowercase_btree.py
BlackDynamite/run_zeo.py
BlackDynamite/runselector.py
BlackDynamite/selector.py
BlackDynamite/zeoobject.py
BlackDynamite/coating/__init__.py
BlackDynamite/coating/bashCoat.py
BlackDynamite/coating/pbsCoat.py
BlackDynamite/coating/sgeCoat.py
BlackDynamite/coating/slurmCoat.py
BlackDynamite/scripts/__init__.py
BlackDynamite/scripts/bash_completion.sh
BlackDynamite/scripts/bd_zeo_server.py
BlackDynamite/scripts/canYouDigIt.py
BlackDynamite/scripts/cleanRuns.py
BlackDynamite/scripts/clone.py
BlackDynamite/scripts/createDB.py
BlackDynamite/scripts/createJobs.py
BlackDynamite/scripts/createRuns.py
BlackDynamite/scripts/createUser.py
BlackDynamite/scripts/enterRun.py
BlackDynamite/scripts/fix_zeodb.py
BlackDynamite/scripts/getJobInfo.py
BlackDynamite/scripts/getRunInfo.py
BlackDynamite/scripts/launchRuns.py
BlackDynamite/scripts/launch_daemon.py
BlackDynamite/scripts/mvRuns.py
BlackDynamite/scripts/open_zeodb.py
BlackDynamite/scripts/plotRuns.py
BlackDynamite/scripts/pull.py
BlackDynamite/scripts/pushQuantity.py
BlackDynamite/scripts/reset.py
BlackDynamite/scripts/saveBDStudy.py
BlackDynamite/scripts/streamlitInfo.py
BlackDynamite/scripts/studyInfo.py
BlackDynamite/scripts/updateRuns.py
blackdynamite-1.3.5.dist-info/licenses/COPYING.txt
blackdynamite-1.3.5.dist-info/METADATA
blackdynamite-1.3.5.dist-info/WHEEL
blackdynamite-1.3.5.dist-info/entry_points.txt
blackdynamite-1.3.5.dist-info/top_level.txt
blackdynamite-1.3.5.dist-info/RECORD
