Metadata-Version: 2.4
Name: blackdynamite
Version: 1.3.5
Summary: Scientific Parametric Study Tool
Author-email: Guillaume Anciaux <guillaume.anciaux@epfl.ch>
License: GPL-3.0-or-later
Project-URL: homepage, https://gitlab.com/ganciaux/blackdynamite
Project-URL: repository, https://gitlab.com/ganciaux/blackdynamite
Project-URL: documentation, https://blackdynamite.readthedocs.io/en/latest/
Requires-Python: >=3.10
License-File: COPYING.txt
Requires-Dist: numpy>=1.24.1
Requires-Dist: argcomplete>=2.0.0
Requires-Dist: psycopg2-binary>=2.9.5
Requires-Dist: pyparsing>=3.0.9
Requires-Dist: zeo>=6.1
Requires-Dist: zodb>=6.1
Requires-Dist: tqdm>=4.64.1
Requires-Dist: psutil>=5.9.4
Requires-Dist: tabulate>=0.9.0
Requires-Dist: pyyaml>=6.0
Requires-Dist: matplotlib>=3.6.3
Requires-Dist: traitlets>=5.9.0
Requires-Dist: ipython>=8.11.0
Requires-Dist: pandas>=2.2.3
Requires-Dist: gitpython>=3.1.44
Requires-Dist: deprecated>=1.2.18
Requires-Dist: lazy-loader>=0.4
Provides-Extra: dev
Requires-Dist: pytest>=7.2.1; extra == "dev"
Requires-Dist: pep8>=1.7.1; extra == "dev"
Dynamic: license-file
